{"docType": "DELCN", "carrier": "PROGRESSIVE", "extractorType": "HEURISTIC", "docFields": [{"fieldId": "4U-kzIoBvXK8o90gG2o2", "fieldName": "POLICY_NUMBER"}, {"fieldId": "4k8KzYoBvXK8o90gA2pc", "fieldName": "EFFECTIVE_DATE"}, {"fieldId": "408OzYoBvXK8o90gImrO", "fieldName": "VIN"}, {"fieldId": "5E8SzYoBvXK8o90gEGqC", "fieldName": "COLLISION_COVERAGE"}, {"fieldId": "5U8TzYoBvXK8o90gDWpp", "fieldName": "COMPREHENSIVE_COVERAGE"}, {"fieldId": "_WC624oBkNrrPX-9OtR2", "fieldName": "INSURED_ADDRESS_STREET"}, {"fieldId": "AGC724oBkNrrPX-9LNU1", "fieldName": "INSURED_ADDRESS_ZIP_CODE"}, {"fieldId": "AWDe3ooBkNrrPX-9pdWM", "fieldName": "LENDER_LISTED_AS_LIENHOLDER_DESCRIPTION"}, {"fieldId": "AmCp34oBkNrrPX-9NtWX", "fieldName": "DATE_OF_NOTICE"}, {"fieldId": "SLRX9osBXophz0DWuFtR", "fieldName": "COMPREHENSIVE_COVERAGE"}, {"fieldId": "g7RY9osBXophz0DWYluP", "fieldName": "COLLISION_COVERAGE"}, {"fieldName": "VEHICLE_YEAR", "fieldId": "IP8hoZABGSRuDTJmWQlK"}, {"fieldName": "VEHICLE_YEAR", "fieldId": "JP_dpZABGSRuDTJmhgnc"}, {"fieldName": "VEHICLE_MAKE", "fieldId": "If8ioZABGSRuDTJmYAky"}, {"fieldId": "I__ApZABGSRuDTJmhgkQ", "fieldName": "VEHICLE_MAKE"}, {"fieldId": "Iv89oZABGSRuDTJmxAn5", "fieldName": "CHANGE_EFFECTIVE_DATE"}, {"fieldId": "Vf9su5ABGSRuDTJmlQqJ", "fieldName": "REASON_FOR_CHANGE"}, {"fieldId": "Vv9tu5ABGSRuDTJmbQrR", "fieldName": "ACCIDENT_LIABILITY_INSURANCE"}, {"fieldId": "V_9uu5ABGSRuDTJmGAob", "fieldName": "PERSON_LIABILITY_INSURANCE"}, {"fieldId": "WP9uu5ABGSRuDTJmdwog", "fieldName": "PROPERTY_LIABILITY_INSURANCE"}, {"fieldId": "Wf9uu5ABGSRuDTJm2QqC", "fieldName": "PHYSICAL_DAMAGE_COVERAGE"}, {"fieldId": "Wv9vu5ABGSRuDTJmSgrP", "fieldName": "COMBINED_LIMIT_LIABILITY_INSURANCE"}, {"fieldId": "W_9vu5ABGSRuDTJmuwqT", "fieldName": "EXCLUDED_DRIVERS_NAME_LAST_NAME"}, {"fieldId": "XP9wu5ABGSRuDTJmGQp5", "fieldName": "EXCLUDED_DRIVERS_NAME_FIRST_NAME"}, {"fieldId": "Xf9wu5ABGSRuDTJmgQpZ", "fieldName": "LENDER_LISTED_AS_ADDITIONAL_NAMED_INSURED_DESCRIPTION"}, {"fieldId": "pv_51ZABGSRuDTJmDJGR", "fieldName": "EXPIRATION_DATE"}, {"fieldId": "-ADg6JABGSRuDTJmmaYh", "fieldName": "LENDER_LISTED_AS_LIENHOLDER_DESCRIPTION"}, {"fieldId": "XAGuBJEBGSRuDTJmL2Xp", "fieldName": "POLICY_NUMBER"}, {"fieldId": "7gV2apEBGSRuDTJmcH5W", "fieldName": "INSURED_NAME_LAST_NAME_COMPANY_NAME"}, {"fieldId": "7wV3apEBGSRuDTJmSX4E", "fieldName": "ALTERNATE_INSURED_NAME_LAST_NAME_COMPANY_NAME"}]}