{
    "fieldName": "VEHICLE_YEAR",
    "docType": "DECLN",
    "carrier": "COMMON",
    "match": [
        {
            "regex": "\\bVEHICLE(?::)?\\b",
            "pageNumber": "1",
            "direction": "Vertical"
        },
        {
            "regex": "\\b(VEH|VEHICLE)(?::)?\\b",
            "pageNumber": "1",
            "direction": "Horizontal"
        },
        {
            "regex": "\\b(YR|YEAR)\\b",
            "pageNumber": "1",
            "direction": "Vertical"
        },
        {
            "regex": "\\b(YEAR|YR)(?::)?\\b",
            "pageNumber": "1",
            "direction": "Horizontal"
        },
        {
            "regex": "\\bNAMED\\sAS\\sLOSS\\sPAYEE\\sFOR\\b",
            "pageNumber": "1",
            "direction": "Horizontal"
        }
    ],
    "not_match": []
}